vertex_tensorboard_logger/__init__.py
vertex_tensorboard_logger/client.py
vertex_tensorboard_logger/factory.py
vertex_tensorboard_logger/interface.py
vertex_tensorboard_logger/product.py
vertex_tensorboard_logger-0.1.1.dist-info/METADATA
vertex_tensorboard_logger-0.1.1.dist-info/WHEEL
vertex_tensorboard_logger-0.1.1.dist-info/RECORD
