Metadata-Version: 2.1
Name: vertex_tensorboard_logger
Version: 0.1.1
Summary: logger to log information to vertex ai experiments and it's tensorboards
Author: giridhar-gitspace
Author-email: gkannappan@suki.ai
Requires-Python: >=3.10,<3.11
Classifier: Programming Language :: Python :: 3
Classifier: Programming Language :: Python :: 3.10
Requires-Dist: google-cloud-aiplatform[tensorboard] (>=1.84.0,<2.0.0)
Requires-Dist: protobuf (==3.20.3)
Requires-Dist: tensorflow (>=2.18.0,<3.0.0)
